{
  "project_info": {
    "project_number": "292476590194",
    "firebase_url": "https://examenandroid2-8f9c6.firebaseio.com",
    "project_id": "examenandroid2-8f9c6",
    "storage_bucket": "examenandroid2-8f9c6.appspot.com"
  },
  "client": [
    {
      "client_info": {
        "mobilesdk_app_id": "1:292476590194:android:3adfd5ecea540ef6",
        "android_client_info": {
          "package_name": "com.example.tay.examen2trimestre"
        }
      },
      "oauth_client": [
        {
          "client_id": "292476590194-jsf6peov1mfim4g8v0o86ba98oeln1bl.apps.googleusercontent.com",
          "client_type": 1,
          "android_info": {
            "package_name": "com.example.tay.examen2trimestre",
            "certificate_hash": "c9e206c1a68424ea2f1ff22dd66b37c7646d143f"
          }
        },
        {
          "client_id": "292476590194-ue3p21l4d55n8si9go7pkmencss295v6.apps.googleusercontent.com",
          "client_type": 3
        }
      ],
      "api_key": [
        {
          "current_key": "AIzaSyAugsMiHkQl6CjMyFegiTjhjV91EY3gdUw"
        }
      ],
      "services": {
        "analytics_service": {
          "status": 1
        },
        "appinvite_service": {
          "status": 2,
          "other_platform_oauth_client": [
            {
              "client_id": "292476590194-ue3p21l4d55n8si9go7pkmencss295v6.apps.googleusercontent.com",
              "client_type": 3
            }
          ]
        },
        "ads_service": {
          "status": 2
        }
      }
    }
  ],
  "configuration_version": "1"
}